py_netchat_server-0.3.7.data/scripts/server_run
server/__init__.py
server/client.py
server/server.py
server/server_gui.py
server/common/__init__.py
server/common/decos.py
server/common/descripters.py
server/common/errors.py
server/common/metaclasses.py
server/common/params.py
server/common/utils.py
server/logs/__init__.py
server/logs/config_client_log.py
server/logs/config_server_log.py
server/server/__init__.py
server/server/add_user.py
server/server/config_window.py
server/server/core.py
server/server/database.py
server/server/main_window.py
server/server/remove_user.py
server/server/stat_window.py
py_netchat_server-0.3.7.dist-info/METADATA
py_netchat_server-0.3.7.dist-info/WHEEL
py_netchat_server-0.3.7.dist-info/top_level.txt
py_netchat_server-0.3.7.dist-info/RECORD
